base_operations_pkg/__init__.py
base_operations_pkg_unique_gabriel_1234-0.0.2.dist-info/METADATA
base_operations_pkg_unique_gabriel_1234-0.0.2.dist-info/WHEEL
base_operations_pkg_unique_gabriel_1234-0.0.2.dist-info/top_level.txt
base_operations_pkg_unique_gabriel_1234-0.0.2.dist-info/RECORD
