Metadata-Version: 2.1
Name: base-operations-pkg-unique-gabriel-1234
Version: 0.0.2
Summary: მარტივი კლასი ძირითადი მათემატიკური ოპერაციებისთვის.
Author: თქვენი სახელი
Author-email: თქვენი-მეილი@example.com
Classifier: Programming Language :: Python :: 3
Classifier: Operating System :: OS Independent
Requires-Python: >=3.6
